procfile_manager/__init__.py
procfile_manager/__main__.py
procfile_manager/command.py
procfile_manager-0.0.3.dist-info/LICENSE.txt
procfile_manager-0.0.3.dist-info/METADATA
procfile_manager-0.0.3.dist-info/WHEEL
procfile_manager-0.0.3.dist-info/entry_points.txt
procfile_manager-0.0.3.dist-info/top_level.txt
procfile_manager-0.0.3.dist-info/RECORD
