Metadata-Version: 2.1
Name: procfile-manager
Version: 0.0.3
Summary: A Python module to manage Procfiles, running them in the first place, with as little restrictions as possible.
Home-page: https://github.com/christophevg/py-procfile-manager
Author: Christophe VG
License: MIT
Keywords: procfile
Platform: UNKNOWN
Classifier: Environment :: Console
Classifier: Development Status :: 4 - Beta
Classifier: Intended Audience :: Developers
Classifier: Intended Audience :: System Administrators
Classifier: Topic :: Software Development
Classifier: License :: OSI Approved :: MIT License
Classifier: Programming Language :: Python
Classifier: Programming Language :: Python :: 2.7
Classifier: Programming Language :: Python :: 3.7
Requires-Dist: python-dotenv
